<?xml version="1.0" encoding="utf-8"?>
<edmx:Edmx Version="1.0" xmlns:edmx="http://schemas.microsoft.com/ado/2007/06/edmx" xmlns:m="http://schemas.microsoft.com/ado/2007/08/dataservices/metadata" xmlns:sap="http://www.sap.com/Protocols/SAPData">
    <edmx:DataServices m:DataServiceVersion="2.0">
        <Schema Namespace="ZVEND_DETAILS_SRV" xml:lang="en" sap:schema-version="1" xmlns="http://schemas.microsoft.com/ado/2008/09/edm">
            <EntityType Name="ZLEDGER" sap:content-version="1">
                <Key>
                    <PropertyRef Name="Mandt"/>
                    <PropertyRef Name="Lifnr"/>
                </Key>
                <Property Name="Mandt" Type="Edm.String" Nullable="false" MaxLength="3" sap:unicode="false" sap:label="Client" sap:creatable="false" sap:updatable="false" sap:sortable="false" sap:filterable="false"/>
                <Property Name="Lifnr" Type="Edm.String" Nullable="false" MaxLength="10" sap:unicode="false" sap:label="Vendor" sap:creatable="false" sap:updatable="false" sap:sortable="false" sap:filterable="false"/>
                <Property Name="Name1" Type="Edm.String" Nullable="false" MaxLength="30" sap:unicode="false" sap:label="Name 1" sap:creatable="false" sap:updatable="false" sap:sortable="false" sap:filterable="false"/>
                <Property Name="Obalance" Type="Edm.Decimal" Nullable="false" Precision="14" Scale="3" sap:unicode="false" sap:label="Amount in LC" sap:creatable="false" sap:updatable="false" sap:sortable="false" sap:filterable="false"/>
                <Property Name="Debit" Type="Edm.Decimal" Nullable="false" Precision="14" Scale="3" sap:unicode="false" sap:label="Amount in LC" sap:creatable="false" sap:updatable="false" sap:sortable="false" sap:filterable="false"/>
                <Property Name="Credit" Type="Edm.Decimal" Nullable="false" Precision="14" Scale="3" sap:unicode="false" sap:label="Amount in LC" sap:creatable="false" sap:updatable="false" sap:sortable="false" sap:filterable="false"/>
                <Property Name="Cbalance" Type="Edm.Decimal" Nullable="false" Precision="14" Scale="3" sap:unicode="false" sap:label="Amount in LC" sap:creatable="false" sap:updatable="false" sap:sortable="false" sap:filterable="false"/>
            </EntityType>
            <EntityType Name="so_vend" sap:content-version="1">
                <Key>
                    <PropertyRef Name="Mandt"/>
                    <PropertyRef Name="Zlifnr"/>
                </Key>
                <Property Name="Mandt" Type="Edm.String" Nullable="false" MaxLength="3" sap:unicode="false" sap:label="Client" sap:creatable="false" sap:updatable="false" sap:sortable="false" sap:filterable="false"/>
                <Property Name="Ztype" Type="Edm.String" Nullable="false" MaxLength="30" sap:unicode="false" sap:label="type" sap:creatable="false" sap:updatable="false" sap:sortable="false" sap:filterable="false"/>
                <Property Name="Zlifnr" Type="Edm.String" Nullable="false" MaxLength="10" sap:unicode="false" sap:label="Vendor" sap:creatable="false" sap:updatable="false" sap:sortable="false" sap:filterable="false"/>
                <Property Name="Zperiod" Type="Edm.String" Nullable="false" MaxLength="2" sap:unicode="false" sap:label="Period" sap:creatable="false" sap:updatable="false" sap:sortable="false" sap:filterable="false"/>
                <Property Name="Zflag" Type="Edm.String" Nullable="false" MaxLength="1" sap:unicode="false" sap:label="Flag" sap:creatable="false" sap:updatable="false" sap:sortable="false" sap:filterable="false"/>
            </EntityType>
            <EntityType Name="zdropdown" sap:content-version="1">
                <Key>
                    <PropertyRef Name="zvalue"/>
                </Key>
                <Property Name="zvalue" Type="Edm.Single" Nullable="false" sap:unicode="false" sap:creatable="false" sap:updatable="false" sap:sortable="false" sap:filterable="false"/>
            </EntityType>
            <EntityType Name="ZWR" sap:content-version="1">
                <Key>
                    <PropertyRef Name="Zlifnr"/>
                </Key>
                <Property Name="Mandt" Type="Edm.String" Nullable="false" MaxLength="3" sap:unicode="false" sap:label="Client" sap:creatable="false" sap:updatable="false" sap:sortable="false" sap:filterable="false"/>
                <Property Name="Zlifnr" Type="Edm.String" Nullable="false" MaxLength="10" sap:unicode="false" sap:label="Vendor" sap:creatable="false" sap:updatable="false" sap:sortable="false" sap:filterable="false"/>
                <Property Name="Zperiod" Type="Edm.String" Nullable="false" MaxLength="2" sap:unicode="false" sap:label="Period" sap:creatable="false" sap:updatable="false" sap:sortable="false" sap:filterable="false"/>
                <Property Name="Zflag" Type="Edm.String" Nullable="false" MaxLength="1" sap:unicode="false" sap:label="Flag" sap:creatable="false" sap:updatable="false" sap:sortable="false" sap:filterable="false"/>
                <Property Name="Ztype" Type="Edm.String" Nullable="false" MaxLength="30" sap:unicode="false" sap:label="type" sap:creatable="false" sap:updatable="false" sap:sortable="false" sap:filterable="false"/>
            </EntityType>
            <EntityType Name="ZWOR" sap:content-version="1">
                <Key>
                    <PropertyRef Name="Zlifnr"/>
                </Key>
                <Property Name="Mandt" Type="Edm.String" Nullable="false" MaxLength="3" sap:unicode="false" sap:label="Client" sap:creatable="false" sap:updatable="false" sap:sortable="false" sap:filterable="false"/>
                <Property Name="Zlifnr" Type="Edm.String" Nullable="false" MaxLength="10" sap:unicode="false" sap:label="Vendor" sap:creatable="false" sap:updatable="false" sap:sortable="false" sap:filterable="false"/>
                <Property Name="Zperiod" Type="Edm.String" Nullable="false" MaxLength="2" sap:unicode="false" sap:label="Period" sap:creatable="false" sap:updatable="false" sap:sortable="false" sap:filterable="false"/>
                <Property Name="Zflag" Type="Edm.String" Nullable="false" MaxLength="1" sap:unicode="false" sap:label="Flag" sap:creatable="false" sap:updatable="false" sap:sortable="false" sap:filterable="false"/>
                <Property Name="Ztype" Type="Edm.String" Nullable="false" MaxLength="30" sap:unicode="false" sap:label="type" sap:creatable="false" sap:updatable="false" sap:sortable="false" sap:filterable="false"/>
            </EntityType>
            <EntityType Name="ZVEND_DETAILS" sap:content-version="1">
                <Key>
                    <PropertyRef Name="Mandt"/>
                    <PropertyRef Name="Lifnr"/>
                </Key>
                <Property Name="Mandt" Type="Edm.String" Nullable="false" MaxLength="3" sap:unicode="false" sap:label="Client" sap:creatable="false" sap:updatable="false" sap:sortable="false" sap:filterable="false"/>
                <Property Name="Fulladdress" Type="Edm.String" Nullable="false" MaxLength="300" sap:unicode="false" sap:label="Character 300" sap:creatable="false" sap:updatable="false" sap:sortable="false" sap:filterable="false"/>
                <Property Name="Lifnr" Type="Edm.String" Nullable="false" MaxLength="10" sap:unicode="false" sap:label="Vendor" sap:creatable="false" sap:updatable="false" sap:sortable="false" sap:filterable="false"/>
                <Property Name="Name" Type="Edm.String" Nullable="false" MaxLength="30" sap:unicode="false" sap:label="Name 1" sap:creatable="false" sap:updatable="false" sap:sortable="false" sap:filterable="false"/>
                <Property Name="Wrbtr" Type="Edm.Decimal" Nullable="false" Precision="24" Scale="3" sap:unicode="false" sap:unit="Waers" sap:label="Amount" sap:creatable="false" sap:updatable="false" sap:sortable="false" sap:filterable="false"/>
                <Property Name="Waers" Type="Edm.String" Nullable="false" MaxLength="5" sap:unicode="false" sap:label="Currency" sap:creatable="false" sap:updatable="false" sap:sortable="false" sap:filterable="false" sap:semantics="currency-code"/>
                <Property Name="STCD1" Type="Edm.String" Nullable="false" MaxLength="16" sap:unicode="false" sap:label="GSTIN" sap:creatable="false" sap:updatable="false" sap:sortable="false" sap:filterable="false"/>
                <Property Name="Status" Type="Edm.String" Nullable="false" MaxLength="20" sap:unicode="false" sap:label="Vendor Status" sap:creatable="false" sap:updatable="false" sap:sortable="false" sap:filterable="false"/>
            </EntityType>
            <EntityType Name="zvendor_avtive" sap:content-version="1">
                <Key>
                    <PropertyRef Name="Mandt"/>
                    <PropertyRef Name="Zlifnr"/>
                </Key>
                <Property Name="Mandt" Type="Edm.String" Nullable="false" MaxLength="3" sap:unicode="false" sap:label="Client" sap:creatable="false" sap:updatable="false" sap:sortable="false" sap:filterable="false"/>
                <Property Name="Zlifnr" Type="Edm.String" Nullable="false" MaxLength="10" sap:unicode="false" sap:label="Vendor" sap:creatable="false" sap:updatable="false" sap:sortable="false" sap:filterable="false"/>
                <Property Name="Zperiod" Type="Edm.String" Nullable="false" MaxLength="2" sap:unicode="false" sap:label="Period" sap:creatable="false" sap:updatable="false" sap:sortable="false" sap:filterable="false"/>
                <Property Name="Zflag" Type="Edm.String" Nullable="false" MaxLength="1" sap:unicode="false" sap:label="Flag" sap:creatable="false" sap:updatable="false" sap:sortable="false" sap:filterable="false"/>
            </EntityType>
            <EntityContainer Name="ZVEND_DETAILS_SRV_Entities" m:IsDefaultEntityContainer="true" sap:supported-formats="atom json xlsx">
                <EntitySet Name="ZLEDGERSet" EntityType="ZVEND_DETAILS_SRV.ZLEDGER" sap:creatable="false" sap:updatable="false" sap:deletable="false" sap:pageable="false" sap:content-version="1"/>
                <EntitySet Name="so_vendSet" EntityType="ZVEND_DETAILS_SRV.so_vend" sap:creatable="false" sap:updatable="false" sap:deletable="false" sap:pageable="false" sap:content-version="1"/>
                <EntitySet Name="zdropdownSet" EntityType="ZVEND_DETAILS_SRV.zdropdown" sap:creatable="false" sap:updatable="false" sap:deletable="false" sap:pageable="false" sap:addressable="false" sap:content-version="1"/>
                <EntitySet Name="ZWRSet" EntityType="ZVEND_DETAILS_SRV.ZWR" sap:creatable="false" sap:updatable="false" sap:deletable="false" sap:pageable="false" sap:content-version="1"/>
                <EntitySet Name="ZWORSet" EntityType="ZVEND_DETAILS_SRV.ZWOR" sap:creatable="false" sap:updatable="false" sap:deletable="false" sap:pageable="false" sap:content-version="1"/>
                <EntitySet Name="ZVEND_DETAILSSet" EntityType="ZVEND_DETAILS_SRV.ZVEND_DETAILS" sap:creatable="false" sap:updatable="false" sap:deletable="false" sap:pageable="false" sap:content-version="1"/>
                <EntitySet Name="zvendor_avtiveSet" EntityType="ZVEND_DETAILS_SRV.zvendor_avtive" sap:creatable="false" sap:updatable="false" sap:deletable="false" sap:pageable="false" sap:content-version="1"/>
            </EntityContainer>
            <atom:link rel="self" href="http://103.248.233.172:8003/sap/opu/odata/sap/ZVEND_DETAILS_SRV/$metadata" xmlns:atom="http://www.w3.org/2005/Atom"/>
            <atom:link rel="latest-version" href="http://103.248.233.172:8003/sap/opu/odata/sap/ZVEND_DETAILS_SRV/$metadata" xmlns:atom="http://www.w3.org/2005/Atom"/>
        </Schema>
    </edmx:DataServices>
</edmx:Edmx>